setup.py
DisneyDisp/__init__.py
DisneyDisp/_confidence.py
DisneyDisp/_disparity.py
DisneyDisp/_process_epi.py
DisneyDisp/_radiance.py
DisneyDisp/_scale.py
DisneyDisp/_score.py
DisneyDisp/clif2lf.py
DisneyDisp/disparity.py
DisneyDisp/dmap2hdf5.py
DisneyDisp/imgs2lf.py
DisneyDisp/lf2epi.py
DisneyDisp.egg-info/PKG-INFO
DisneyDisp.egg-info/SOURCES.txt
DisneyDisp.egg-info/dependency_links.txt
DisneyDisp.egg-info/not-zip-safe
DisneyDisp.egg-info/requires.txt
DisneyDisp.egg-info/top_level.txt
bin/clif2lf
bin/disparity
bin/dmap2hdf5
bin/imgs2lf
bin/lf2epi