Metadata-Version: 1.0
Name: DisneyDisp
Version: 0.1.11
Summary: A free python implementation of the "Scene Reconstruction from High Spatio-Angular Resolution Light Fields". For more information oabout the algorithm  see https://www.disneyresearch.com/project/lightfields/. Currently we support CPU computing only. To finish computation in reasnable time you will need several cores and a lot of ram (the more the better).
Home-page: https://github.com/manuSrep/DisneyDispPy.git
Author: Marcel Gutsche, Manuel Tuschen
Author-email: Manuel_Tuschen@web.de
License: GPL3 License
Platform: UNKNOWN
